bolt/__init__.py
bolt/django.py
bolt/flask.py
testbolt-0.0.17.dist-info/LICENSE
testbolt-0.0.17.dist-info/METADATA
testbolt-0.0.17.dist-info/WHEEL
testbolt-0.0.17.dist-info/top_level.txt
testbolt-0.0.17.dist-info/RECORD
